celebalucid/__init__.py
celebalucid/cka.py
celebalucid/generator.py
celebalucid/utils.py
celebalucid/models/__init__.py
celebalucid/models/inceptionv1.py
celebalucid/models/manipulator.py
celebalucid/res/layer_info.txt
celebalucid-0.1.5.3.dist-info/LICENSE
celebalucid-0.1.5.3.dist-info/METADATA
celebalucid-0.1.5.3.dist-info/WHEEL
celebalucid-0.1.5.3.dist-info/top_level.txt
celebalucid-0.1.5.3.dist-info/RECORD
