Metadata-Version: 2.1
Name: celebalucid
Version: 0.1.5.3
Summary: Analysing Clarity's InceptionV1 network after transfer learning on CelebA dataset.
Home-page: http://pypi.python.org/pypi/celebalucid/
Author: Gergely Papp
Author-email: gergopool@gmail.com
License: LICENSE
Platform: UNKNOWN
Classifier: Programming Language :: Python :: 3
Classifier: License :: OSI Approved :: MIT License
Classifier: Operating System :: OS Independent
Requires-Python: >=3.6
Requires-Dist: torch-lucent
Requires-Dist: dotmap
Requires-Dist: numpy
Requires-Dist: tqdm
Requires-Dist: opencv-python
Requires-Dist: pandas
